gldas/GLDASp4_landmask_025d.nc4
gldas/__init__.py
gldas/download.py
gldas/grid.py
gldas/interface.py
gldas/reshuffle.py
gldas/utils.py
gldas-0.7.2.dist-info/licenses/AUTHORS.rst
gldas-0.7.2.dist-info/licenses/LICENSE.txt
gldas-0.7.2.dist-info/METADATA
gldas-0.7.2.dist-info/WHEEL
gldas-0.7.2.dist-info/entry_points.txt
gldas-0.7.2.dist-info/top_level.txt
gldas-0.7.2.dist-info/RECORD
