Metadata-Version: 2.4
Name: gldas
Version: 0.7.2
Summary: Readers and converters for data from the GLDAS Noah Land Surface Model.
Home-page: https://github.com/TUW-GEO/gldas
Author: TU Wien
Author-email: support@qa4sm.eu
License: mit
Project-URL: Documentation, https://gldas.readthedocs.io/en/latest/
Platform: any
Classifier: Development Status :: 4 - Beta
Classifier: Programming Language :: Python
License-File: LICENSE.txt
License-File: AUTHORS.rst
Requires-Dist: importlib-metadata; python_version < "3.8"
Requires-Dist: pyproj
Requires-Dist: pygeogrids
Requires-Dist: numpy
Requires-Dist: pygeobase
Requires-Dist: datedown>=0.4
Requires-Dist: trollsift
Requires-Dist: netCDF4
Requires-Dist: pyresample
Requires-Dist: repurpose
Requires-Dist: pynetcf
Provides-Extra: testing
Requires-Dist: pytest-cov; extra == "testing"
Requires-Dist: coverage; extra == "testing"
Requires-Dist: pytest; extra == "testing"
Provides-Extra: building
Requires-Dist: setuptools-scm; extra == "building"
Requires-Dist: setuptools; extra == "building"
Requires-Dist: wheel; extra == "building"
Requires-Dist: packaging; extra == "building"
Requires-Dist: build; extra == "building"
Requires-Dist: twine; extra == "building"
Dynamic: license-file
